pysustrans/__init__.py
pysustrans/association.py
pysustrans/correlation.py
pysustrans/pysustrans.py
pysustrans/sustrans.py
pysustrans-0.0.112.dist-info/LICENCE.txt
pysustrans-0.0.112.dist-info/METADATA
pysustrans-0.0.112.dist-info/WHEEL
pysustrans-0.0.112.dist-info/top_level.txt
pysustrans-0.0.112.dist-info/RECORD
