Metadata-Version: 2.1
Name: pysustrans
Version: 0.0.112
Summary: pysustran is a statistical Python package for Transportation data analysis.
Author: Rahul Raoniar
Author-email: rahul.raoniar@outlook.com
License: MIT
Platform: UNKNOWN
Classifier: Programming Language :: Python :: 3
Requires-Python: >=3.8
License-File: LICENCE.txt
Requires-Dist: numpy
Requires-Dist: scipy
Requires-Dist: pandas
Requires-Dist: matplotlib
Requires-Dist: seaborn
